fredtools/__init__.py
fredtools/ft_braggPeak.py
fredtools/ft_displayImg.py
fredtools/ft_dvh.py
fredtools/ft_imgAnalyse.py
fredtools/ft_imgGetSubimg.py
fredtools/ft_imgManipulate.py
fredtools/ft_misc.py
fredtools/ft_simTools.py
fredtools/ft_spotAnalyse.py
fredtools/smparallel.py
fredtools/ft_gammaIndex/__init__.py
fredtools/ft_gammaIndex/gammaIndex.py
fredtools/ft_gammaIndex/libFredGI.so
fredtools/ft_imgIO/__init__.py
fredtools/ft_imgIO/dicom_io.py
fredtools/ft_imgIO/dij_io.py
fredtools/ft_imgIO/influenceMatrix_io.py
fredtools/ft_imgIO/map3d_io.py
fredtools/ft_imgIO/mhd_io.py
fredtools/ft_imgIO/other_io.py
fredtools/ft_optimisation/__init__.py
fredtools/ft_optimisation/ft_optimiseBeamPositions.py
fredtools/ft_optimisation/ft_preoptimizer.py
fredtools-0.7.28.dist-info/METADATA
fredtools-0.7.28.dist-info/WHEEL
fredtools-0.7.28.dist-info/top_level.txt
fredtools-0.7.28.dist-info/RECORD
