Metadata-Version: 2.1
Name: fredtools
Version: 0.7.28
Summary: FRED tools is a collection of python functions for image manipulation and analysis. See more on https://github.com/jasqs/FREDtools.
Home-page: https://www.fredtools.ifj.edu.pl/
Author: FRED Collaboration
Author-email: jan.gajewski@ifj.edu.pl
Project-URL: Repository, https://github.com/jasqs/FREDtools
Project-URL: FRED MC, http://www.fred-mc.org/
Classifier: Programming Language :: Python :: 3
Classifier: License :: OSI Approved :: GNU Lesser General Public License v3 (LGPLv3)
Classifier: Operating System :: OS Independent
Requires-Python: >=3.10,<4.0
Requires-Dist: dicompyler-core (>=0.5.6)
Requires-Dist: fitz (>=0.0.1.dev2)
Requires-Dist: fredtools (>=0.7.24)
Requires-Dist: ipython (>=8.25.0)
Requires-Dist: ipywidgets (>=8.1.3)
Requires-Dist: itk (>=5.4.0)
Requires-Dist: landaupy (>=0.1)
Requires-Dist: lmfit (>=1.3.1)
Requires-Dist: matplotlib (>=3.9.0)
Requires-Dist: numpy (>=1.24.2)
Requires-Dist: pandas (>=2.2.2)
Requires-Dist: psutil (>=5.9.4)
Requires-Dist: pydicom (>=2.4.4)
Requires-Dist: PyYAML (>=6.0.1)
Requires-Dist: PyYAML (>=5.4.1)
Requires-Dist: scipy (>=1.13.1)
Requires-Dist: Shapely (>=2.0.4)
Requires-Dist: SimpleITK (>=2.3.1)
Requires-Dist: uproot (>=5.3.7)
